AUTHORS
LICENSE
MANIFEST.in
README.rst
setup.cfg
setup.py
django_viewlet.egg-info/PKG-INFO
django_viewlet.egg-info/SOURCES.txt
django_viewlet.egg-info/dependency_links.txt
django_viewlet.egg-info/not-zip-safe
django_viewlet.egg-info/requires.txt
django_viewlet.egg-info/top_level.txt
viewlet/__init__.py
viewlet/api.py
viewlet/cache.py
viewlet/compat.py
viewlet/conf.py
viewlet/const.py
viewlet/exceptions.py
viewlet/library.py
viewlet/models.py
viewlet/urls.py
viewlet/views.py
viewlet/loaders/__init__.py
viewlet/loaders/django_loader.py
viewlet/loaders/jinja2_loader.py
viewlet/templatetags/__init__.py
viewlet/templatetags/viewlets.py
viewlet/tests/__init__.py
viewlet/tests/compat.py
viewlet/tests/test_viewlet.py
viewlet/tests/urls.py
viewlet/tests/utils.py