Metadata-Version: 1.1
Name: django-viewlet
Version: 1.5.1
Summary: Render template parts with extended cache control.
Home-page: http://github.com/5monkeys/django-viewlet
Author: Jonas Lundberg
Author-email: jonas@5monkeys.se
License: MIT
Download-URL: https://github.com/5monkeys/django-viewlet/tarball/1.5.1
Keywords: django,template,cache,view,subview,decorator,refresh,invalidate
Platform: any
Classifier: Programming Language :: Python
Classifier: Programming Language :: Python :: 2.6
Classifier: Programming Language :: Python :: 2.7
Classifier: Framework :: Django
Classifier: Natural Language :: English
Classifier: Environment :: Web Environment
Classifier: Intended Audience :: Developers
Classifier: License :: OSI Approved :: MIT License
Classifier: Operating System :: OS Independent
Classifier: Topic :: Internet :: WWW/HTTP
Classifier: Topic :: Utilities
Classifier: Topic :: Software Development :: Libraries :: Python Modules
